autowallpaper/__init__.py
autowallpaper/autowallpaper.py
autowallpaper/daemon.py
autowallpaper-0.0.2.dist-info/LICENSE
autowallpaper-0.0.2.dist-info/METADATA
autowallpaper-0.0.2.dist-info/WHEEL
autowallpaper-0.0.2.dist-info/top_level.txt
autowallpaper-0.0.2.dist-info/RECORD
