Metadata-Version: 2.1
Name: autowallpaper
Version: 0.0.2
Summary: Package that helps you create your own wallpaper changing service
Home-page: https://github.com/pskelkar74/autowallpaper
Author: Pranav Kelkar
Author-email: pskelkar74@gmail.com
License: UNKNOWN
Project-URL: Bug Tracker, https://github.com/pskelkar74/autowallpaper/issues
Platform: UNKNOWN
Classifier: Programming Language :: Python :: 3
Classifier: License :: OSI Approved :: MIT License
Requires-Python: >=3.6
License-File: LICENSE
